git_extract/__init__.py
git_extract/cli.py
git_extract/files.py
git_extract-1.1.5.dist-info/entry_points.txt
git_extract-1.1.5.dist-info/LICENSE.md
git_extract-1.1.5.dist-info/WHEEL
git_extract-1.1.5.dist-info/METADATA
git_extract-1.1.5.dist-info/RECORD
